sbomdiff/__init__.py
sbomdiff/cli.py
sbomdiff/cyclonedx_parser.py
sbomdiff/output.py
sbomdiff/spdx_parser.py
sbomdiff/version.py
sbomdiff-0.5.6.dist-info/LICENSE
sbomdiff-0.5.6.dist-info/METADATA
sbomdiff-0.5.6.dist-info/WHEEL
sbomdiff-0.5.6.dist-info/entry_points.txt
sbomdiff-0.5.6.dist-info/top_level.txt
sbomdiff-0.5.6.dist-info/RECORD
